playbook/__init__.py
playbook/__version__.py
playbook/cli.py
playbook/command.py
playbook/config.py
playbook/main.py
playbook/utils.py
playbook_youqu-2025.8.1.dist-info/METADATA
playbook_youqu-2025.8.1.dist-info/WHEEL
playbook_youqu-2025.8.1.dist-info/entry_points.txt
playbook_youqu-2025.8.1.dist-info/licenses/LICENSE
playbook_youqu-2025.8.1.dist-info/RECORD
