Metadata-Version: 2.1
Name: playbook-youqu
Version: 2025.8.1
Summary: Task Scheduling System
Author-email: wangpeng <781757836@qq.com>
License: GPL2.0
License-File: LICENSE
Requires-Python: >=3.6
Requires-Dist: click
Requires-Dist: funnylog2
Requires-Dist: nocmd
